deluge_cmd/__init__.py
deluge_cmd/cli.py
deluge_cmd/deluge_dls.py
deluge_cmd/deluge_dmv.py
deluge_cmd-0.4.0.dist-info/entry_points.txt
deluge_cmd-0.4.0.dist-info/LICENSE
deluge_cmd-0.4.0.dist-info/WHEEL
deluge_cmd-0.4.0.dist-info/METADATA
deluge_cmd-0.4.0.dist-info/RECORD
