Metadata-Version: 2.1
Name: deluge-cmd
Version: 0.4.0
Summary: Command line tools to manage Synthstrom deluge SD card contents.
Home-page: https://github.com/mupaduw/deluge-cmd
License: MIT
Author: Chris B Chamberlain
Author-email: chrisbc@artisan.co.nz
Requires-Python: >=3.8,<4.0
Classifier: Development Status :: 2 - Pre-Alpha
Classifier: Environment :: Console
Classifier: Intended Audience :: Other Audience
Classifier: License :: OSI Approved :: MIT License
Classifier: Natural Language :: English
Classifier: Programming Language :: Python :: 3
Classifier: Programming Language :: Python :: 3.10
Classifier: Programming Language :: Python :: 3.8
Classifier: Programming Language :: Python :: 3.9
Classifier: Topic :: Multimedia :: Sound/Audio
Provides-Extra: dev
Provides-Extra: doc
Provides-Extra: test
Requires-Dist: click (>=8.1.3,<9.0.0)
Requires-Dist: deluge-card (>=0.7.0,<0.8.0)
